server_admintools/__init__.py
server_admintools/gitlab.py
server_admintools/rsync.py
server_admintools/sudo.py
server_admintools-0.1.1.data/scripts/fetch-backup
server_admintools-0.1.1.data/scripts/gitlab-backup
server_admintools-0.1.1.data/scripts/gitlab-repo-backup
server_admintools-0.1.1.dist-info/METADATA
server_admintools-0.1.1.dist-info/RECORD
server_admintools-0.1.1.dist-info/WHEEL
server_admintools-0.1.1.dist-info/top_level.txt
test/__init__.py
