Metadata-Version: 2.1
Name: server-admintools
Version: 0.1.1
Summary: An XDCC File Downloader based on the irclib framework
Home-page: https://gitlab.namibsun.net/namibsun/python/server-admintools
Author: Hermann Krumrey
Author-email: hermann@krumreyh.com
License: GNU GPL3
Platform: UNKNOWN
Classifier: License :: OSI Approved :: GNU General Public License v3 (GPLv3)
